Workbook

Sheet Direct_Materials
A1: Subsystem | B1: Total Cost [€]
A2: Processing & Control | B2: 5
A3: Measurement Chain | B3: 15
A4: HMI | B4: 30
A5: Power System | B5: 10
A6: PCB & Passives | B6: 14
A7: Protective Case | B7: 220
A8: Miscellanous Mechanical Components | B8: 10
A9: Load Cells | B9: 2844
A10: Total | B10: =SUM(B2:B9) -> 3148

Sheet Raw_Materials
A1: Material | B1: Quantity [kg] | C1: Cost per kg [€/kg] | D1: Cost [€]
A2: Polycarbonate | B2: 0.12 | C2: 3.5 | D2: =B2*C2 -> 0.42
A3: ABS | B3: 0.08 | C3: 2.5 | D3: =B3*C3 -> 0.2
A4: 5052 Aluminum | B4: 6.6 | C4: 4 | D4: =B4*C4 -> 26.4
A5: EVA/PU Foam | B5: 0.96 | C5: 2 | D5: =B5*C5 -> 1.92
C7: Total | D7: =SUM(D2:D5) -> 28.94

Sheet Labor
A1: Annual Working Hours [h] | B1: 4284
A2: Hourly Wage [€/h] | B2: 20
A3: Annual Labour Cost [€] | B3: =B2*B1 -> 85680
A4: Labour Cost per Unit [€/unit] | B4: =B3/150 -> 571.2

Sheet Machine_Dep
A1: Machine | B1: Total Cost [€] | C1: Annual Depreciation Rate | D1: Depreciation Per Year [€/year] | E1: Machine Hourly Rate [€/h] | F1: Machine Hours per Unit [h/unit] | G1: Machine Cost per Unit [€/unit] | K1: Real Machine availability [minutes/year]
A2: 3D Printer | B2: 800 | C2: 0.2 | D2: =B2*C2 -> 160 | E2: =D2/(K2/60) -> 0.15392015 | F2: 6.7 | G2: =E2*F2 -> 1.031265 | K2: 62370
A3: 4-Axis CNC Milling Machine | B3: 70000 | C3: 0.1 | D3: =B3*C3 -> 7000 | E3: =D3/(K3/60) -> 5.2910053 | F3: 2.7166667 | G3: =E3*F3 -> 14.373898 | K3: 79380
A4: 3-Axis CNC Contour Machine | B4: 50000 | C4: 0.1 | D4: =B4*C4 -> 5000 | E4: =D4/(K4/60) -> 4.0700041 | F4: 2.2166667 | G4: =E4*F4 -> 9.0218424 | K4: 73710
A5: 3-Axis CNC Milling Machine | B5: 9000 | C5: 0.1 | D5: =B5*C5 -> 900 | E5: =D5/(K5/60) -> 0.68027211 | F5: 1.5833333 | G5: =E5*F5 -> 1.0770975 | K5: 79380
A6: Extrusion Press | B6: 100000 | C6: 0.1 | D6: =B6*C6 -> 10000 | E6: =D6/(K6/60) -> 5.8788948 | F6: 0.28333333 | G6: =E6*F6 -> 1.6656869 | K6: 102060
A7: Drill | B7: 150 | C7: 0.1 | D7: =B7*C7 -> 15 | E7: =D7/(K7/60) -> 0.013227513 | F7: 0.23333333 | G7: =E7*F7 -> 0.0030864198 | K7: 68040
A8: Reamer | B8: 30 | C8: 0.1 | D8: =B8*C8 -> 3 | E8: =D8/(K8/60) -> 0.0031746032 | F8: 0.26666667 | G8: =E8*F8 -> 0.00084656085 | K8: 56700
A9: Laser Cutter | B9: 40000 | C9: 0.1 | D9: =B9*C9 -> 4000 | E9: =D9/(K9/60) -> 3.0234316 | F9: 0.41666667 | G9: =E9*F9 -> 1.2597632 | K9: 79380
A10: Welding Plant | B10: 500 | C10: 0.1 | D10: =B10*C10 -> 50 | E10: =D10/(K10/60) -> 0.052910053 | F10: 1.2833333 | G10: =E10*F10 -> 0.067901235 | K10: 56700
A11: Automated Pick-and-Place Machine | B11: 3500 | C11: 0.1 | D11: =B11*C11 -> 350 | E11: =D11/(K11/60) -> 0.24691358 | F11: 0.18333333 | G11: =E11*F11 -> 0.04526749 | K11: 85050
A12: Reflow Oven | B12: 360 | C12: 0.05 | D12: =B12*C12 -> 18 | E12: =D12/(K12/60) -> 0.011204482 | F12: 0.34166667 | G12: =E12*F12 -> 0.0038281979 | K12: 96390
A13: Hand Soldering Station | B13: 200 | C13: 0.05 | D13: =B13*C13 -> 10 | E13: =D13/(K13/60) -> 0.015117158 | F13: 0.41666667 | G13: =E13*F13 -> 0.0062988158 | K13: 39690
A14: Total | G14: =SUM(G2:G13) -> 28.556781

Sheet Utility
A1: Machine | B1: Power [kW] | C1: Cost per kWh [€/kWh] | D1: Machine Hours per Unit [h/unit] | E1: Utility Cost per Unit [€/unit]
A2: 3D Printer | B2: 0.15 | C2: 0.04 | D2: 6.7 | E2: =B2*C2*D2 -> 0.0402
A3: 4-Axis CNC Milling Machine | B3: 8 | C3: 2.1 | D3: 2.7166667 | E3: =B3*C3*D3 -> 45.64
A4: 3-Axis CNC Contour Machine | B4: 2.7 | C4: 2 | D4: 2.2166667 | E4: =B4*C4*D4 -> 11.97
A5: 3-Axis CNC Milling Machine | B5: 1 | C5: 2 | D5: 1.5833333 | E5: =B5*C5*D5 -> 3.1666667
A6: Extrusion Press | B6: 10 | C6: 0.8 | D6: 0.28333333 | E6: =B6*C6*D6 -> 2.2666667
A7: Drill | B7: 0.05 | C7: 0.02 | D7: 0.23333333 | E7: =B7*C7*D7 -> 0.00023333333
A8: Reamer | B8: 0 | C8: 0 | D8: 0.26666667 | E8: =B8*C8*D8 -> 0
A9: Laser Cutter | B9: 4.5 | C9: 1.17 | D9: 0.41666667 | E9: =B9*C9*D9 -> 2.19375
A10: Welding Plant | B10: 2.5 | C10: 0.65 | D10: 1.2833333 | E10: =B10*C10*D10 -> 2.0854167
A11: Automated Pick-and-Place Machine | B11: 0.2 | C11: 0.05 | D11: 0.18333333 | E11: =B11*C11*D11 -> 0.0018333333
A12: Reflow Oven | B12: 1.2 | C12: 0.31 | D12: 0.34166667 | E12: =B12*C12*D12 -> 0.1271
A13: Hand Soldering Station | B13: 0.07 | C13: 0.02 | D13: 0.41666667 | E13: =B13*C13*D13 -> 0.00058333333
A14: Total | E14: =SUM(E2:E13) -> 67.49245

Sheet Rent
A1: Rent per square meter [€/m^2] | B1: 7
A2: Additional Cost percent [-] | B2: 0.15 | C2: =(B1*B3*12)*B2 -> 1260
A3: Size [m^2] | B3: 100
A4: Total Annual Rent [€/year] | B4: =B1*B3*12*(1+B2) -> 9660
A5: Rent per Unit [€/unit] | B5: =B4/150 -> 64.4

Sheet Summary
A1: Item | B1: € per Unit
A2: Direct Material Costs [€/unit] | B2: =Direct_Materials!B10 -> 3148
A3: Raw Material Costs [€/unit] | B3: =Raw_Materials!D7 -> 28.94
A4: Material Overhead [-] | B4: 0.05 | C4: =B4*(B2+B3) -> 158.847
A5: Total Material Costs [€/unit] | B5: =(B2+B3)*(1+B4) -> 3335.787
A6: Labor Costs [€/unit] | B6: =Labor!B4 -> 571.2
A7: Machine Costs [€/unit] | B7: =Machine_Dep!G14 -> 28.556781
A8: Utility Costs [€/unit] | B8: =Utility!E14 -> 67.49245
A9: Rent [€/unit] | B9: =Rent!B5 -> 64.4
A10: Manufacturing Costs [€/unit] | B10: =B6+B7+B8+B9 -> 731.64923
A11: Production Costs [€/unit] | B11: =B5+B10 -> 4067.4362
A13: Admin Overhead | B13: 0.08 | C13: =$B$11*B13 -> 325.3949
A14: Marketing & Sales Overhead | B14: 0.15 | C14: =$B$11*B14 -> 610.11543
A15: COGS [€/unit] | B15: =B11*(1+B13+B14) -> 5002.9466
A17: Profit Margin | B17: 0.3 | C17: =B17*B15 -> 1500.884
A18: Cash Selling Price | B18: =B15*(1+B17) -> 6503.8305
A19: Distributor Commission | B19: 0.1 | C19: =B18*B19 -> 650.38305
A20: Final Offer Price | B20: =B18*(1+B19) -> 7154.2136
